{
	"geode": "5.3.0",
	"gd": {
		"win": "2.2081",
		"android": "2.2081",
		"mac": "2.2081",
		"ios": "2.2081"
	},
	"id": "cosmella.coin-shower",
	"name": "Soggy Shower",
	"version": "v1.0.2-beta.2000000999999999996",
	"developer": "Cosmella",
	"description": "Soggy Soggy Soggy Soggy Soggy Soggy Soggy Soggy Soggy Soggy Soggy Soggy Soggy Soggy Soggy Soggy Soggy Soggy Soggy Soggy Soggy Soggy Soggy Soggy Soggy Soggy Soggy Soggy Soggy Soggy Soggy Soggy Soggy Soggy Soggy Soggy Soggy Soggy Soggy Soggy Soggy Soggy Soggy Soggy Soggy Soggy Soggy Soggy Soggy Soggy Soggy Soggy Soggy Soggy Soggy Soggy Soggy Soggy Soggy Soggy Soggy Soggy Soggy Soggy Soggy Soggy Soggy Soggy Soggy Soggy Soggy Soggy ",
	"settings": {
		"soggy": {
			"name": "Toggle Soggy mode",
			"description": "Soggy",
			"type": "bool",
			"default": true
		},
		"toggle": {
			"name": "Toggle Normal mode",
			"description": "Soggy go shower toggle",
			"type": "bool",
			"default": true
		},
		"practice-mode": {
			"name": "Toggle Practice mode",
			"description": "Soggy go shower toggle in practice mode",
			"type": "bool",
			"default": false
		}
	},
	"resources": {"sprites": ["soggy.png"]},
	"tags": [
		"joke",
		"offline","gameplay",
		"content"
	]
}
